CSP_Solver/CSP.py
CSP_Solver/Util.py
CSP_Solver/__init__.py
CSP_Solver/ArcConsistency/ArcConsistency_Util.py
CSP_Solver/ArcConsistency/Arc_Consistent_Backtracking.py
CSP_Solver/Forward_Checking/ForwardChecking.py
CSP_Solver/Forward_Checking/ForwardChecking_MRV.py
CSP_Solver/Forward_Checking/ForwardChecking_MRV_LCV.py
CSP_Solver/General_LocalSearch_Algorithms/Simulated_Annealing.py
CSP_Solver/General_LocalSearch_Algorithms/Util.py
CSP_Solver/General_LocalSearch_Algorithms/local_beam_search.py
CSP_Solver/Genetic_Algo/Genetic_Solver.py
CSP_Solver/Genetic_Algo/Genetic_Util.py
CSP_Solver/Hill_Climbing/Hill_Climbing.py
CSP_Solver/Hill_Climbing/Hill_Climbing_Util.py
CSP_Solver/Hill_Climbing/Hill_Climbing_chooseRandom.py
CSP_Solver/Hill_Climbing/Hill_Climbing_greedyBias.py
CSP_Solver/Hill_Climbing/Hill_Climbing_with_restarts.py
CSP_Solver/Novel_Approach/My_Algorithm.py
CSP_Solver/Trivial_Algorithms/BackTrack.py
CSP_Solver/Trivial_Algorithms/dfs.py
CSP_Solver-0.1.2.dist-info/METADATA
CSP_Solver-0.1.2.dist-info/WHEEL
CSP_Solver-0.1.2.dist-info/top_level.txt
CSP_Solver-0.1.2.dist-info/RECORD
