Metadata-Version: 2.1
Name: CSP-Solver
Version: 0.1.2
Summary: Library to solve Constraint satisfation problems
Home-page: https://github.com/LezendarySandwich/Generic-CSP-Solver
Author: Sanskar Mani
Author-email: mani.1@iitj.ac.in
License: UNKNOWN
Platform: UNKNOWN
Classifier: Programming Language :: Python :: 3
Classifier: License :: OSI Approved :: MIT License
Classifier: Operating System :: OS Independent
Requires-Python: >=3.0.0
Requires-Dist: numpy
Requires-Dist: sortedcontainers
